coreauth/AuthenticatedCredentials.py
coreauth/Authenticator.py
coreauth/__init__.py
coreauth/exception/AuthenticatorError.py
coreauth/exception/UnableToAuthenticateError.py
coreauth/exception/__init__.py
coreauth/repository/AuthRepository.py
coreauth/repository/__init__.py
coreauth/utility/__init__.py
coreauth/utility/auth_utilities.py
persuader_technology_automata_auth-0.1.6.dist-info/LICENSE
persuader_technology_automata_auth-0.1.6.dist-info/METADATA
persuader_technology_automata_auth-0.1.6.dist-info/WHEEL
persuader_technology_automata_auth-0.1.6.dist-info/top_level.txt
persuader_technology_automata_auth-0.1.6.dist-info/RECORD
